setup.py
acrawriter/__init__.py
acrawriter/tests.py
acrawriter.egg-info/PKG-INFO
acrawriter.egg-info/SOURCES.txt
acrawriter.egg-info/dependency_links.txt
acrawriter.egg-info/requires.txt
acrawriter.egg-info/top_level.txt
acrawriter/django/__init__.py
acrawriter/sqlalchemy/__init__.py